LICENSE
MANIFEST.in
OpenSees-LICENSE
README.rst
requirements.txt
setup.cfg
setup.py
examples/readme_example.png
o3seespy/__about__.py
o3seespy/__init__.py
o3seespy/base_model.py
o3seespy/cc.py
o3seespy/exceptions.py
o3seespy/extensions.py
o3seespy/mp.py
o3seespy/mptools.py
o3seespy/opensees_instance.py
o3seespy/results.py
o3seespy.egg-info/PKG-INFO
o3seespy.egg-info/SOURCES.txt
o3seespy.egg-info/dependency_links.txt
o3seespy.egg-info/not-zip-safe
o3seespy.egg-info/requires.txt
o3seespy.egg-info/top_level.txt
o3seespy/command/__init__.py
o3seespy/command/algorithm.py
o3seespy/command/analysis.py
o3seespy/command/beam_integration.py
o3seespy/command/common.py
o3seespy/command/constraints.py
o3seespy/command/friction_model.py
o3seespy/command/fsicmds.py
o3seespy/command/geom_transf.py
o3seespy/command/ground_motion.py
o3seespy/command/integrator.py
o3seespy/command/layer.py
o3seespy/command/mat_recorder_options.csv
o3seespy/command/mesh.py
o3seespy/command/node.py
o3seespy/command/numberer.py
o3seespy/command/parallelcmds.py
o3seespy/command/patch.py
o3seespy/command/pattern.py
o3seespy/command/rayleigh.py
o3seespy/command/recorder.py
o3seespy/command/region.py
o3seespy/command/reliabilitycmds.py
o3seespy/command/section.py
o3seespy/command/senscmds.py
o3seespy/command/system.py
o3seespy/command/test.py
o3seespy/command/test_check.py
o3seespy/command/time_series.py
o3seespy/command/element/__init__.py
o3seespy/command/element/base_element.py
o3seespy/command/element/beam_column.py
o3seespy/command/element/bearing.py
o3seespy/command/element/brick.py
o3seespy/command/element/cable.py
o3seespy/command/element/contact.py
o3seespy/command/element/joint.py
o3seespy/command/element/link.py
o3seespy/command/element/misc.py
o3seespy/command/element/other_up.py
o3seespy/command/element/pfem.py
o3seespy/command/element/quadrilateral.py
o3seespy/command/element/soil_foundation.py
o3seespy/command/element/tetrahedron.py
o3seespy/command/element/triangular.py
o3seespy/command/element/truss.py
o3seespy/command/element/uc_san_diego_up.py
o3seespy/command/element/zero_length.py
o3seespy/command/nd_material/__init__.py
o3seespy/command/nd_material/base_material.py
