Metadata-Version: 2.1
Name: o3seespy
Version: 3.4.0.2
Summary: Object-oriented native Python version of OpenSees
Home-page: UNKNOWN
Author: Maxim Millen & Minjie Zhu
Author-email: mmi46@uclive.ac.nz
License: MIT with OpenSees License
Platform: UNKNOWN
Classifier: Development Status :: 3 - Alpha
Classifier: Intended Audience :: Science/Research
Classifier: Topic :: Scientific/Engineering
Classifier: Programming Language :: Python :: 3
Requires-Python: >=3
Provides-Extra: test
License-File: LICENSE
